wildapies/__init__.py
wildapies/parser.py
wildapies-1.1.1.dist-info/METADATA
wildapies-1.1.1.dist-info/WHEEL
wildapies-1.1.1.dist-info/top_level.txt
wildapies-1.1.1.dist-info/RECORD
